oscar_vehicle_api/__init__.py
oscar_vehicle_api/asp.py
oscar_vehicle_api/control.py
oscar_vehicle_api/log.py
oscar_vehicle_api/log_viz.py
oscar_vehicle_api/loops.py
oscar_vehicle_api/oscar_vehicle_api.py
oscar_vehicle_api/protocol.py
oscar_vehicle_api/vehicle_interface.py
oscar_vehicle_api-2.0.dist-info/METADATA
oscar_vehicle_api-2.0.dist-info/WHEEL
oscar_vehicle_api-2.0.dist-info/top_level.txt
oscar_vehicle_api-2.0.dist-info/RECORD
