Metadata-Version: 2.1
Name: oscar-vehicle-api
Version: 2.0
Summary: OSCAR Vehicle API
Home-page: https://gitlab.com/starline/oscar_vehicle_api
Author: Nikolay Dema
Author-email: ndema2301@gmail.com
License: UNKNOWN
Keywords: oscar,vehicle,api
Platform: UNKNOWN
Classifier: Programming Language :: Python :: 2
Classifier: Programming Language :: Python :: 2.6
Classifier: Programming Language :: Python :: 2.7
Classifier: Programming Language :: Python :: 3
Classifier: Programming Language :: Python :: 3.6
Classifier: Programming Language :: Python :: 3.7
Classifier: Programming Language :: Python :: 3.8
Classifier: Programming Language :: Python :: 3.9
Classifier: License :: OSI Approved :: Apache Software License
Classifier: Operating System :: OS Independent
Requires-Python: >=2.6
Requires-Dist: pyserial (>=3.4)
